{
  "lastChecks": {
    "code_health": 1773249215,
    "dependencies": 1773144600,
    "docs": 1773157200,
    "performance": 1773296649,
    "security": 1773148200,
    "quick_check_2026-03-12_11": 1743286080
  },
  "issuesFound": {
    "high": 0,
    "medium": 0,
    "low": 0,
    "total": 0
  },
  "issuesFixed": {
    "auto": 11,
    "manual": 0
  },
  "lastReport": "2026-03-12 11:21",
  "totalScans": 101,
  "autoFixEnabled": true,
  "scanInterval": 86400,
  "capabilities": {
    "selfDiscovery": true,
    "autoFix": true,
    "longTermMemory": true,
    "qualityControl": true,
    "continuousLearning": true
  },
  "enhancementLevel": "Stage 1 Complete",
  "recentScans": {
    "quick_check_2026-03-12_11": {
      "date": "2026-03-12 11:21",
      "result": "✅ 优秀",
      "notes": "系统稳定(6天21小时53分), 负载0.00, 内存53%, 磁盘78%. Docker: 权限前端(1小时)✅ 权限后端(10小时)✅ 权限MySQL(11小时)✅. 外网: 管理后台200✅ API健康(/admin/api/health)200✅. 技能管理系统完整实现(68文件/10,371行代码/4数据库表/6API端点). 系统稳定运行, 代码健康度: ⭐⭐⭐⭐⭐"
    },
    "quick_check_2026-03-12_10": {
      "date": "2026-03-12 10:17",
      "result": "✅ 优秀",
      "notes": "系统稳定(6天21小时9分), 负载0.00, 内存53%, 磁盘78%. Docker: 权限前端(1小时)✅ 权限后端(10小时)✅ 权限MySQL(11小时)✅. 外网: 管理后台200✅ API健康(/admin/api/health)200✅. 权限系统v1.0.0运行稳定, 累计100次扫描, 11次自动修复. 代码健康度: ⭐⭐⭐⭐⭐"
    },
    "quick_check_2026_03_12_09": {
      "date": "2026-03-12 09:47",
      "result": "✅ 优秀",
      "notes": "系统稳定(6天20小时38分), 负载0.18, 内存53%, 磁盘78%. Docker: 权限前端(43分钟)✅ 权限后端(10小时)✅ 权限MySQL(10小时)✅. 外网: 管理后台200✅ API健康(/admin/api/health)200✅. /api/health路径不存在是正常的,正确路径是/admin/api/health. 权限系统v1.0.0已部署并提交到git(30d1849). 代码健康度: ⭐⭐⭐⭐⭐"
    }
  }
}